fuzstr/__init__.py
fuzstr/_modidx.py
fuzstr/core.py
fuzstr-0.0.8.dist-info/LICENSE
fuzstr-0.0.8.dist-info/METADATA
fuzstr-0.0.8.dist-info/WHEEL
fuzstr-0.0.8.dist-info/entry_points.txt
fuzstr-0.0.8.dist-info/top_level.txt
fuzstr-0.0.8.dist-info/RECORD
