Metadata-Version: 2.1
Name: fuzstr
Version: 0.0.8
Summary: fuzzy string matching
Home-page: https://github.com/dsm-72/fuzstr
Author: dsm-72
Author-email: sumner.magruder@yale.edu
License: Apache Software License 2.0
Keywords: nbdev jupyter notebook python fuzstr fuzzy strings str fuzz fuzzywuzzy
Classifier: Development Status :: 4 - Beta
Classifier: Intended Audience :: Developers
Classifier: Natural Language :: English
Classifier: Programming Language :: Python :: 3.11
Classifier: License :: OSI Approved :: Apache Software License
Requires-Python: >=3.11
License-File: LICENSE
Requires-Dist: atyp
Requires-Dist: regsyn
Requires-Dist: ispec
Requires-Dist: pstr
Requires-Dist: aspec
Provides-Extra: dev
